{
  "main": {
    "id": "1e7bd2e549360168",
    "type": "split",
    "children": [
      {
        "id": "ce86807590d0a410",
        "type": "tabs",
        "children": [
          {
            "id": "b349feb590f349f3",
            "type": "leaf",
            "state": {
              "type": "empty",
              "state": {}
            }
          }
        ]
      }
    ],
    "direction": "vertical"
  },
  "left": {
    "id": "cd457b9823b69425",
    "type": "split",
    "children": [
      {
        "id": "400a347c06bbd810",
        "type": "tabs",
        "children": [
          {
            "id": "e2851abea1e9fb60",
            "type": "leaf",
            "state": {
              "type": "file-explorer",
              "state": {
                "sortOrder": "alphabetical"
              }
            }
          },
          {
            "id": "e978d2a2a48b1dc7",
            "type": "leaf",
            "state": {
              "type": "search",
              "state": {
                "query": "",
                "matchingCase": false,
                "explainSearch": false,
                "collapseAll": false,
                "extraContext": false,
                "sortOrder": "alphabetical"
              }
            }
          },
          {
            "id": "046b4f0dcf9a4d7e",
            "type": "leaf",
            "state": {
              "type": "starred",
              "state": {}
            }
          }
        ]
      }
    ],
    "direction": "horizontal",
    "width": 300
  },
  "right": {
    "id": "c556ac04022b3a5f",
    "type": "split",
    "children": [
      {
        "id": "27dc41af7a021f21",
        "type": "tabs",
        "children": [
          {
            "id": "0bce334139b7bbd7",
            "type": "leaf",
            "state": {
              "type": "backlink",
              "state": {
                "collapseAll": false,
                "extraContext": false,
                "sortOrder": "alphabetical",
                "showSearch": false,
                "searchQuery": "",
                "backlinkCollapsed": true,
                "unlinkedCollapsed": true
              }
            }
          },
          {
            "id": "00b85705f5b1cd68",
            "type": "leaf",
            "state": {
              "type": "outgoing-link",
              "state": {
                "linksCollapsed": false,
                "unlinkedCollapsed": true
              }
            }
          },
          {
            "id": "52e14168be35c90d",
            "type": "leaf",
            "state": {
              "type": "tag",
              "state": {
                "sortOrder": "frequency",
                "useHierarchy": true
              }
            }
          },
          {
            "id": "e3933e17cf316e27",
            "type": "leaf",
            "state": {
              "type": "outline",
              "state": {}
            }
          },
          {
            "id": "0e89ff4c1e0ec9af",
            "type": "leaf",
            "state": {
              "type": "advanced-tables-toolbar",
              "state": {}
            }
          }
        ],
        "currentTab": 1
      }
    ],
    "direction": "horizontal",
    "width": 300,
    "collapsed": true
  },
  "ribbon": {
    "mostRecentAction": ""
  },
  "active": "e2851abea1e9fb60",
  "lastOpenFiles": [
    "2022-10-14.md",
    "Sistemi operativi/File System.md",
    "Teoria ed elaborazione dei segnali/Serie e trasformata di Fourier.md",
    "Sistemi operativi/Introduzione ai SO.md",
    "Sistemi operativi/images/Pasted image 20221013222021.png",
    "Sistemi operativi/images/Pasted image 20221013222210.png",
    "Sistemi operativi/images/Pasted image 20221013222521.png",
    "Sistemi operativi/images/Pasted image 20221013222916.png",
    "Teoria ed elaborazione dei segnali/Grandezze di interesse sui segnali.md",
    "prova.md"
  ]
}